LICENSE
MANIFEST.in
README.md
requirements.txt
setup.py
alidns/__init__.py
alidns/alidns.py
alidns.egg-info/PKG-INFO
alidns.egg-info/SOURCES.txt
alidns.egg-info/dependency_links.txt
alidns.egg-info/entry_points.txt
alidns.egg-info/not-zip-safe
alidns.egg-info/requires.txt
alidns.egg-info/top_level.txt