Metadata-Version: 1.2
Name: alidns
Version: 2.0.2
Summary: Aliyun DNS Update Tool.
Home-page: https://github.com/luoyeah/alidns
Author: luoyeah
Author-email: luoyeah_ilku@foxmail.com
License: GPLv3
Keywords: alidns,aliyun,ddns,dns
Platform: any
Classifier: Development Status :: 5 - Production/Stable
Classifier: Environment :: Console
Classifier: Intended Audience :: Developers
Classifier: License :: OSI Approved :: GNU General Public License v3 (GPLv3)
Classifier: Natural Language :: English
Classifier: Natural Language :: Chinese (Simplified)
Classifier: Programming Language :: Python :: 3
Classifier: Topic :: Internet
Classifier: Topic :: Software Development :: Libraries :: Python Modules
Requires-Python: >=3.0
